MANIFEST.in
README.rst
requirements.txt
setup.py
mk_blender_scr/__init__.py
mk_blender_scr/default_color.ini
mk_blender_scr/jmol_color.csv
mk_blender_scr/vesta_color.ini
mk_blender_scr.egg-info/PKG-INFO
mk_blender_scr.egg-info/SOURCES.txt
mk_blender_scr.egg-info/dependency_links.txt
mk_blender_scr.egg-info/entry_points.txt
mk_blender_scr.egg-info/requires.txt
mk_blender_scr.egg-info/top_level.txt
mk_blender_scr/blender/__init__.py
mk_blender_scr/blender/default.py
mk_blender_scr/blender/functions.py
mk_blender_scr/blender/make_script.py
mk_blender_scr/io/__init__.py
mk_blender_scr/io/read_elementsini.py
mk_blender_scr/visualize/__init__.py
mk_blender_scr/visualize/by_nglview.py
mk_blender_scr/visualize/color.py
mk_blender_scr/visualize/custum_viewer.py
mk_blender_scr/visualize/functions.py