Metadata-Version: 2.1
Name: mk-blender-scr
Version: 1.0.8
Summary: Create a Python script for Blender from Atoms of ASE.
Home-page: https://shimi-lab.github.io/mk-blender-scr_Document/
Author: Kato Taisetsu
License: UNKNOWN
Keywords: blender ase
Platform: UNKNOWN
